{
  "backlog": {
    "list": {
      "method": "GET",
      "path": "/api/groups/{groupId}/tracking/backlog",
      "response": [
        {
          "backlogItemId": "2c1faa57-8f86-4b8b-93e0-0dcd7cd9612d",
          "groupId": "58e25044-76f4-4d5c-ac5d-7a649f2d3bda",
          "title": "Set up realtime messaging",
          "description": "Implement SignalR hub for chat",
          "status": "Ready",
          "priority": "High",
          "category": "Feature",
          "storyPoints": 5,
          "ownerUserId": "2bf78433-8749-4f02-a683-322a6da5a4b7",
          "ownerDisplayName": "Alice Nguyen",
          "dueDate": "2025-01-15T00:00:00Z",
          "linkedTaskId": "38c33aa0-6a76-4050-a506-20a02a6c82e1",
          "columnId": "4df03a4d-6c93-4a35-99d8-434bfc4e3a52",
          "columnName": "To Do",
          "columnIsDone": false,
          "milestoneId": "7b3acd5c-7993-4fd7-a204-845879f3cb1d",
          "milestoneName": "Sprint 1 Kickoff",
          "createdAt": "2024-12-01T09:00:00Z",
          "updatedAt": "2024-12-05T10:20:00Z"
        }
      ]
    },
    "create": {
      "method": "POST",
      "path": "/api/groups/{groupId}/tracking/backlog",
      "request": {
        "title": "Build profile page",
        "description": "Showcase member info and achievements",
        "priority": "Medium",
        "category": "Feature",
        "storyPoints": 3,
        "dueDate": "2025-01-20T00:00:00Z",
        "ownerUserId": "3db9cbf1-9560-4fe1-9c00-2b5eef58d83a"
      },
      "response": "c5c5a44b-0f4c-4a4d-9c21-5d0a564d596a"
    },
    "update": {
      "method": "PUT",
      "path": "/api/groups/{groupId}/tracking/backlog/{backlogItemId}",
      "request": {
        "title": "Set up realtime messaging",
        "description": "Implement SignalR hub for chat",
        "priority": "High",
        "category": "Feature",
        "storyPoints": 5,
        "dueDate": "2025-01-18T00:00:00Z",
        "status": "InProgress",
        "ownerUserId": "2bf78433-8749-4f02-a683-322a6da5a4b7"
      },
      "response": null
    },
    "archive": {
      "method": "DELETE",
      "path": "/api/groups/{groupId}/tracking/backlog/{backlogItemId}",
      "response": null
    },
    "promote": {
      "method": "POST",
      "path": "/api/groups/{groupId}/tracking/backlog/{backlogItemId}/promote",
      "request": {
        "columnId": "6f2df6d8-4ec8-45b5-92bc-848f91ff9c8b",
        "taskStatus": "InProgress",
        "taskDueDate": "2025-01-18T00:00:00Z"
      },
      "response": "38c33aa0-6a76-4050-a506-20a02a6c82e1"
    }
  },
  "milestones": {
    "list": {
      "method": "GET",
      "path": "/api/groups/{groupId}/tracking/milestones",
      "response": [
        {
          "milestoneId": "7b3acd5c-7993-4fd7-a204-845879f3cb1d",
          "groupId": "58e25044-76f4-4d5c-ac5d-7a649f2d3bda",
          "name": "Sprint 1 Kickoff",
          "status": "InProgress",
          "targetDate": "2025-02-10",
          "completedAt": null,
          "description": "Foundation deliverables",
          "totalItems": 8,
          "completedItems": 3,
          "completionPercent": 0.375,
          "createdAt": "2024-11-25T08:00:00Z",
          "updatedAt": "2024-12-06T07:30:00Z",
          "items": [
            {
              "backlogItemId": "2c1faa57-8f86-4b8b-93e0-0dcd7cd9612d",
              "title": "Set up realtime messaging",
              "status": "Ready",
              "dueDate": "2025-01-15T00:00:00Z",
              "linkedTaskId": "38c33aa0-6a76-4050-a506-20a02a6c82e1",
              "columnName": "To Do",
              "columnIsDone": false
            }
          ]
        }
      ]
    },
    "create": {
      "method": "POST",
      "path": "/api/groups/{groupId}/tracking/milestones",
      "request": {
        "name": "Sprint 2 Delivery",
        "description": "Finalize mobile experience",
        "targetDate": "2025-03-05"
      },
      "response": "9af15676-2d3a-42ad-afb8-5a5f41c2a319"
    },
    "update": {
      "method": "PUT",
      "path": "/api/groups/{groupId}/tracking/milestones/{milestoneId}",
      "request": {
        "name": "Sprint 1 Kickoff",
        "description": "Foundation deliverables",
        "targetDate": "2025-02-12",
        "status": "Completed",
        "completedAt": "2025-02-12T18:45:00Z"
      },
      "response": null
    },
    "delete": {
      "method": "DELETE",
      "path": "/api/groups/{groupId}/tracking/milestones/{milestoneId}",
      "response": null
    },
    "assignItems": {
      "method": "POST",
      "path": "/api/groups/{groupId}/tracking/milestones/{milestoneId}/items",
      "request": {
        "backlogItemIds": [
          "2c1faa57-8f86-4b8b-93e0-0dcd7cd9612d",
          "c5c5a44b-0f4c-4a4d-9c21-5d0a564d596a"
        ]
      },
      "response": null
    },
    "removeItem": {
      "method": "DELETE",
      "path": "/api/groups/{groupId}/tracking/milestones/{milestoneId}/items/{backlogItemId}",
      "response": null
    }
  },
  "comments": {
    "list": {
      "method": "GET",
      "path": "/api/groups/{groupId}/board/tasks/{taskId}/comments",
      "response": [
        {
          "commentId": "f4b58d8d-6dbb-41d0-8fd0-8c7b3e693a8c",
          "taskId": "38c33aa0-6a76-4050-a506-20a02a6c82e1",
          "userId": "2bf78433-8749-4f02-a683-322a6da5a4b7",
          "content": "Deployed SignalR hub to staging",
          "createdAt": "2024-12-06T15:42:00Z"
        }
      ]
    },
    "create": {
      "method": "POST",
      "path": "/api/groups/{groupId}/board/tasks/{taskId}/comments",
      "request": {
        "content": "Can you add retry logic on reconnect?"
      },
      "response": "f4b58d8d-6dbb-41d0-8fd0-8c7b3e693a8c"
    },
    "delete": {
      "method": "DELETE",
      "path": "/api/groups/{groupId}/board/comments/{commentId}",
      "response": null
    }
  },
  "files": {
    "listByGroup": {
      "method": "GET",
      "path": "/api/groups/{groupId}/board/files",
      "response": [
        {
          "fileId": "d9b83c09-9d7f-4f88-9a0f-1157cdb4a8f0",
          "groupId": "58e25044-76f4-4d5c-ac5d-7a649f2d3bda",
          "uploadedBy": "2bf78433-8749-4f02-a683-322a6da5a4b7",
          "uploadedByName": "Alice Nguyen",
          "uploadedByAvatarUrl": "https://cdn.teammy.dev/avatars/alice.png",
          "taskId": "38c33aa0-6a76-4050-a506-20a02a6c82e1",
          "fileName": "sprint-board.png",
          "fileUrl": "https://drive.google.com/uc?id=1abcXYZ",
          "fileType": "image/png",
          "fileSize": 482300,
          "description": "Screenshot for review",
          "createdAt": "2024-12-06T10:05:00Z"
        }
      ]
    },
    "listByTask": {
      "method": "GET",
      "path": "/api/groups/{groupId}/board/tasks/{taskId}/files",
      "response": [
        {
          "fileId": "d9b83c09-9d7f-4f88-9a0f-1157cdb4a8f0",
          "groupId": "58e25044-76f4-4d5c-ac5d-7a649f2d3bda",
          "uploadedBy": "2bf78433-8749-4f02-a683-322a6da5a4b7",
          "uploadedByName": "Alice Nguyen",
          "uploadedByAvatarUrl": "https://cdn.teammy.dev/avatars/alice.png",
          "taskId": "38c33aa0-6a76-4050-a506-20a02a6c82e1",
          "fileName": "sprint-board.png",
          "fileUrl": "https://drive.google.com/uc?id=1abcXYZ",
          "fileType": "image/png",
          "fileSize": 482300,
          "description": "Screenshot for review",
          "createdAt": "2024-12-06T10:05:00Z"
        }
      ]
    },
    "upload": {
      "method": "POST",
      "path": "/api/groups/{groupId}/board/files/upload",
      "request": {
        "contentType": "multipart/form-data",
        "fields": {
          "file": "(binary sprint-notes.pdf)",
          "taskId": "38c33aa0-6a76-4050-a506-20a02a6c82e1",
          "description": "Architecture notes"
        }
      },
      "response": {
        "fileId": "a2fa58f7-15ce-4b4c-ac22-e81f5b8727f4",
        "fileName": "sprint-notes.pdf",
        "fileUrl": "https://drive.google.com/uc?id=1defXYZ",
        "fileType": "application/pdf",
        "fileSize": 143820,
        "taskId": "38c33aa0-6a76-4050-a506-20a02a6c82e1"
      }
    },
    "delete": {
      "method": "DELETE",
      "path": "/api/groups/{groupId}/board/files/{fileId}",
      "response": null
    }
  }
}
